patch/__init__.py
patch/constants.py
patch/debug.py
patch/auth/__init__.py
patch/auth/auth_client.py
patch/auth/auth_forms.py
patch/auth/auth_token.py
patch/cli/__init__.py
patch/cli/patch_click_context.py
patch/cli/phone_number_param_type.py
patch/cli/styled.py
patch/cli/commands/__init__.py
patch/cli/commands/access.py
patch/cli/commands/admin.py
patch/cli/commands/connector.py
patch/cli/commands/dataset.py
patch/cli/commands/destination.py
patch/cli/commands/login.py
patch/cli/commands/logout.py
patch/cli/commands/playground.py
patch/cli/commands/source.py
patch/cli/commands/token.py
patch/cli/commands/user.py
patch/cli/commands/alpha/__init__.py
patch/cli/commands/alpha/package.py
patch/cli/remote/__init__.py
patch/cli/remote/dataset_client.py
patch/cli/remote/source_client.py
patch/cli/tools/__init__.py
patch/cli/tools/base64_encryption.py
patch/cli/tools/config.py
patch/cli/tools/config_interactive.py
patch/cli/tools/config_non_interactive.py
patch/cli/tools/config_spec.py
patch/cli/tools/field_spec.py
patch/cli/tools/filters_reader.py
patch/cli/tools/json_reader.py
patch/cli/tools/connectors/__init__.py
patch/cli/tools/connectors/connector_spec.py
patch/cli/tools/datasets/__init__.py
patch/cli/tools/datasets/curl_renderer.py
patch/cli/tools/datasets/diff_renderer.py
patch/cli/tools/datasets/endpoint_renderer.py
patch/cli/tools/datasets/row_table_renderer.py
patch/cli/tools/destinations/__init__.py
patch/cli/tools/destinations/destination_spec.py
patch/cli/tools/state/__init__.py
patch/cli/tools/state/auth_state_transfer.py
patch/cli/tools/state/bi_directional_state_transfer.py
patch/cli/tools/state/state_transfer.py
patch/cli/tools/tables/__init__.py
patch/cli/tools/tables/renders.py
patch/cli/tools/tables/source_app.css
patch/cli/tools/tables/source_app.py
patch/cli/tools/tables/source_data.py
patch/cli/tools/tables/source_metadata_client.py
patch/cli/tools/tables/state_manager.py
patch/cli/tools/tables/components/__init__.py
patch_cli-0.2.16.dist-info/LICENSE.md
patch_cli-0.2.16.dist-info/METADATA
patch_cli-0.2.16.dist-info/WHEEL
patch_cli-0.2.16.dist-info/entry_points.txt
patch_cli-0.2.16.dist-info/top_level.txt
patch_cli-0.2.16.dist-info/RECORD
