Metadata-Version: 2.1
Name: patch-cli
Version: 0.2.16
Summary: Spin up analytics APIs over your data in minutes, without writing any code.
Home-page: https://www.patch.tech/
Download-URL: https://docs.patch.tech/command-line-interface/installation
Author: Patch Enterprises
Author-email: eng@patch.tech
Project-URL: Changelog, https://patch.releases.live/
Project-URL: Documentation, https://docs.patch.tech/command-line-interface/basic-usage
Project-URL: Twitter, https://twitter.com/Patch_Data
Keywords: data,warehouse,data-warehouse,cli,sdk,patch,patch-tech,analytics,dashboard,graphql,api,dataset,snowflake,bigquery,cache,in-memory-datasets
Classifier: Development Status :: 4 - Beta
Classifier: Environment :: Console
Classifier: Intended Audience :: Developers
Classifier: License :: OSI Approved :: Apache Software License
Classifier: Natural Language :: English
Classifier: Programming Language :: Python :: 3
Classifier: Topic :: Database
Requires-Python: >=3.7
License-File: LICENSE.md
Requires-Dist: appdirs ==1.4.4
Requires-Dist: click ==8.1.3
Requires-Dist: click-aliases ==1.0.1
Requires-Dist: phonenumbers ==8.12.48
Requires-Dist: rich ==12.6.0
Requires-Dist: sgqlc ==16.0
Requires-Dist: requests ==2.27.1
Requires-Dist: textual ==0.7.0
Requires-Dist: PyJWT ==2.4.0
Requires-Dist: pyperclip ==1.8.2
Provides-Extra: build
Requires-Dist: build ==0.8.0 ; extra == 'build'
Requires-Dist: twine ==4.0.2 ; extra == 'build'
Provides-Extra: test
Requires-Dist: pytest ==7.1.2 ; extra == 'test'
Requires-Dist: requests-mock ==1.9.3 ; extra == 'test'
